odoo/addons/l10n_fi_edicode/README.rst
odoo/addons/l10n_fi_edicode/__init__.py
odoo/addons/l10n_fi_edicode/__manifest__.py
odoo/addons/l10n_fi_edicode/data/res_partner_operator_einvoice.xml
odoo/addons/l10n_fi_edicode/i18n/fi.po
odoo/addons/l10n_fi_edicode/i18n/l10n_fi_edicode.pot
odoo/addons/l10n_fi_edicode/models/__init__.py
odoo/addons/l10n_fi_edicode/models/res_company.py
odoo/addons/l10n_fi_edicode/models/res_config_settings.py
odoo/addons/l10n_fi_edicode/models/res_partner.py
odoo/addons/l10n_fi_edicode/models/res_partner_operator_einvoice.py
odoo/addons/l10n_fi_edicode/readme/CONFIGURE.md
odoo/addons/l10n_fi_edicode/readme/CONTRIBUTORS.md
odoo/addons/l10n_fi_edicode/readme/CREDITS.md
odoo/addons/l10n_fi_edicode/readme/DESCRIPTION.md
odoo/addons/l10n_fi_edicode/readme/HISTORY.md
odoo/addons/l10n_fi_edicode/readme/MAINTAINER.rst
odoo/addons/l10n_fi_edicode/security/ir.model.access.csv
odoo/addons/l10n_fi_edicode/static/description/icon.png
odoo/addons/l10n_fi_edicode/static/description/index.html
odoo/addons/l10n_fi_edicode/tests/__init__.py
odoo/addons/l10n_fi_edicode/tests/test_edi_operator.py
odoo/addons/l10n_fi_edicode/tests/test_partner.py
odoo/addons/l10n_fi_edicode/views/menuitems.xml
odoo/addons/l10n_fi_edicode/views/res_company_view.xml
odoo/addons/l10n_fi_edicode/views/res_config_settings_view.xml
odoo/addons/l10n_fi_edicode/views/res_partner_operator_einvoice_view.xml
odoo/addons/l10n_fi_edicode/views/res_partner_view.xml
odoo_addon_l10n_fi_edicode-19.0.1.0.0.2.dist-info/METADATA
odoo_addon_l10n_fi_edicode-19.0.1.0.0.2.dist-info/WHEEL
odoo_addon_l10n_fi_edicode-19.0.1.0.0.2.dist-info/top_level.txt
odoo_addon_l10n_fi_edicode-19.0.1.0.0.2.dist-info/RECORD
