Metadata-Version: 2.1
Name: odoo-addon-l10n_fi_edicode
Version: 19.0.1.0.0.2
Requires-Dist: odoo==19.0.*
Summary: Adds EDI code field and operators
Home-page: https://github.com/OCA/l10n-finland
License: LGPL-3
Author: Futural, Odoo Community Association (OCA), Avoin.Systems
Author-email: support@odoo-community.org
Classifier: Programming Language :: Python
Classifier: Framework :: Odoo
Classifier: Framework :: Odoo :: 19.0
Classifier: License :: OSI Approved :: GNU Lesser General Public License v3 (LGPLv3)
